miditok/__init__.py
miditok/classes.py
miditok/constants.py
miditok/midi_tokenizer.py
miditok/data_augmentation/__init__.py
miditok/data_augmentation/data_augmentation.py
miditok/pytorch_data/__init__.py
miditok/pytorch_data/collators.py
miditok/pytorch_data/datasets.py
miditok/tokenizations/__init__.py
miditok/tokenizations/cp_word.py
miditok/tokenizations/midi_like.py
miditok/tokenizations/mmm.py
miditok/tokenizations/mumidi.py
miditok/tokenizations/octuple.py
miditok/tokenizations/remi.py
miditok/tokenizations/structured.py
miditok/tokenizations/tsd.py
miditok/utils/__init__.py
miditok/utils/utils.py
miditok_for_musiclang-0.0.1.dist-info/LICENSE
miditok_for_musiclang-0.0.1.dist-info/METADATA
miditok_for_musiclang-0.0.1.dist-info/WHEEL
miditok_for_musiclang-0.0.1.dist-info/top_level.txt
miditok_for_musiclang-0.0.1.dist-info/RECORD
