Metadata-Version: 2.1
Name: miditok-for-musiclang
Version: 0.0.1
Summary: A convenient MIDI tokenizer for Deep Learning networks, with multiple encoding strategies
Home-page: https://github.com/MusicLang/MidiTok
Author: Nathan Fradet
License: MIT
Keywords: artificial intelligence,deep learning,transformer,midi,tokenization,music,mir
Classifier: Intended Audience :: Developers
Classifier: Intended Audience :: Science/Research
Classifier: Topic :: Scientific/Engineering :: Artificial Intelligence
Classifier: Topic :: Multimedia :: Sound/Audio :: MIDI
Classifier: License :: OSI Approved :: MIT License
Classifier: Programming Language :: Python :: 3
Classifier: Programming Language :: Python :: 3.7
Classifier: Operating System :: OS Independent
License-File: LICENSE
Requires-Dist: numpy <1.24,>=1.19
Requires-Dist: miditoolkit >=0.1.16
Requires-Dist: tqdm
Requires-Dist: tokenizers >=0.13.0
Requires-Dist: scipy
Requires-Dist: matplotlib
